vertexone_watersmart/__init__.py
vertexone_watersmart/client.py
vertexone_watersmart/exceptions.py
vertexone_watersmart/parsers.py
vertexone_watersmart/providers.py
vertexone_watersmart/sqlite.py
vertexone_watersmart/storage_class.py
vertexone_watersmart-0.1.4.dist-info/LICENSE
vertexone_watersmart-0.1.4.dist-info/METADATA
vertexone_watersmart-0.1.4.dist-info/WHEEL
vertexone_watersmart-0.1.4.dist-info/top_level.txt
vertexone_watersmart-0.1.4.dist-info/RECORD
